useful_forks/__init__.py
useful_forks/api.py
useful_forks/cli.py
useful_forks/models.py
useful_forks/py.typed
useful_forks-0.0.1.dist-info/METADATA
useful_forks-0.0.1.dist-info/WHEEL
useful_forks-0.0.1.dist-info/entry_points.txt
useful_forks-0.0.1.dist-info/RECORD
